timecorr/__init__.py
timecorr/helpers.py
timecorr/simulate.py
timecorr/timecorr.py
timecorr-0.2.0.dist-info/licenses/LICENSE
timecorr-0.2.0.dist-info/METADATA
timecorr-0.2.0.dist-info/WHEEL
timecorr-0.2.0.dist-info/top_level.txt
timecorr-0.2.0.dist-info/RECORD
