Metadata-Version: 2.4
Name: timecorr
Version: 0.2.0
Summary: Compute dynamic correlations, dynamic higher-order correlations, and dynamic graph theoretic measures in timeseries data
Home-page: https://github.com/ContextLab/timecorr
Author: Contextual Dynamics Laboratory
Author-email: contextualdynamics@gmail.com
License: MIT
License-File: LICENSE
Requires-Dist: nose>=1.3.7
Requires-Dist: sphinx>=2.0.0
Requires-Dist: duecredit>=0.7.0
Requires-Dist: hypertools>=0.7.0
Requires-Dist: numpy>=1.14.2
Requires-Dist: scipy>=1.2.1
Requires-Dist: scikit-learn>=0.19.2
Provides-Extra: docs
Requires-Dist: sphinx>=4.0.0; extra == "docs"
Requires-Dist: sphinx-book-theme; extra == "docs"
Requires-Dist: sphinx-gallery; extra == "docs"
Requires-Dist: numpydoc; extra == "docs"
Requires-Dist: nbsphinx; extra == "docs"
Requires-Dist: matplotlib>=2.1.0; extra == "docs"
Requires-Dist: seaborn>=0.8.1; extra == "docs"
Dynamic: author
Dynamic: author-email
Dynamic: description
Dynamic: description-content-type
Dynamic: home-page
Dynamic: license
Dynamic: license-file
Dynamic: provides-extra
Dynamic: requires-dist
Dynamic: summary
